pyarubaswitch/__init__.py
pyarubaswitch/api_engine.py
pyarubaswitch/aruba_switch_client.py
pyarubaswitch/common_ops.py
pyarubaswitch/config_reader.py
pyarubaswitch/get_loop_protect.py
pyarubaswitch/get_mac_table.py
pyarubaswitch/get_port_vlans.py
pyarubaswitch/get_snmpv3_info.py
pyarubaswitch/get_sntp.py
pyarubaswitch/get_stp_info.py
pyarubaswitch/input_parser.py
pyarubaswitch/interface_info.py
pyarubaswitch/lldp_neighbours.py
pyarubaswitch/models.py
pyarubaswitch/system_status.py
pyarubaswitch/telnet_info.py
pyarubaswitch-0.2.3.data/scripts/pyarubaswitch-baseinfo
pyarubaswitch_workflows/__init__.py
pyarubaswitch_workflows/check_desired_vlans.py
pyarubaswitch_workflows/filehandling.py
pyarubaswitch_workflows/get_base_info.py
pyarubaswitch_workflows/get_topology.py
pyarubaswitch_workflows/network_objects.py
pyarubaswitch_workflows/runner.py
tests/__init__.py
tests/basic_test.py
pyarubaswitch-0.2.3.dist-info/LICENSE
pyarubaswitch-0.2.3.dist-info/METADATA
pyarubaswitch-0.2.3.dist-info/WHEEL
pyarubaswitch-0.2.3.dist-info/top_level.txt
pyarubaswitch-0.2.3.dist-info/RECORD
