Metadata-Version: 2.1
Name: pyarubaswitch
Version: 0.2.3
Summary: Python requests based REST-API-Client for aruba switches.
Home-page: https://github.com/federstedt/pyarubaswitch
Author: Daniel Federstedt
Author-email: daniel@braveops.se
Classifier: Programming Language :: Python :: 3
Classifier: License :: OSI Approved :: MIT License
Classifier: Operating System :: OS Independent
Requires-Python: >=3.10
License-File: LICENSE
Requires-Dist: requests
Requires-Dist: PyYAML
Requires-Dist: pydantic
